{
  "$schema": "https://biomejs.dev/schemas/1.8.3/schema.json",
  "files": {
    "ignore": ["dist/**"]
  },
  "organizeImports": {
    "enabled": false
  },
  "linter": {
    "enabled": true,
    "rules": {
      "recommended": true,
      "suspicious": {
        "noExplicitAny": "off",
        "noAssignInExpressions": "info"
      },
      "complexity": {
        "noForEach": "off",
        "noBannedTypes": "off"
      },
      "style": {
        "noParameterAssign": "info",
        "noNonNullAssertion": "info"
      },
      "performance": {
        "noDelete": "off"
      }
    }
  },
  "vcs": {
    "enabled": true,
    "clientKind": "git",
    "useIgnoreFile": true,
    "defaultBranch": "master"
  },
  "formatter": {
    "enabled": true,
    "formatWithErrors": false,
    "indentStyle": "space",
    "indentWidth": 2,
    "lineEnding": "lf",
    "lineWidth": 120,
    "ignore": ["package.json"]
  },
  "javascript": {
    "formatter": {
      "quoteStyle": "double",
      "trailingCommas": "all",
      "semicolons": "asNeeded"
    }
  }
}
